sender/__init__.py
ar_edu_uade_sender-0.1.dist-info/METADATA
ar_edu_uade_sender-0.1.dist-info/WHEEL
ar_edu_uade_sender-0.1.dist-info/top_level.txt
ar_edu_uade_sender-0.1.dist-info/RECORD
