Metadata-Version: 2.1
Name: ar-edu-uade-sender
Version: 0.1
Summary: paquete utilizado para enviar mensajes entre los módulos y el core en un proyecto académico
Home-page: https://github.com/matiasfelau/sender-python
Author: matiasfelau
Author-email: matiasfelau@gmail.com
Classifier: Programming Language :: Python :: 3
Classifier: License :: OSI Approved :: MIT License
Classifier: Operating System :: OS Independent
Requires-Python: >=3.6
Requires-Dist: some-package>=1.0.0
